{"k3791p8c/E+Bgrr6iv94zA==":"logo-marca-1.png","VPflgm0+YBSQmEgiCgeO3w==":"logo-marca-2.png","OB2qi2bCnyIKerbt3Eu8Nw==":"logo-marca-3.png","gHfh68lLxFArI+GCsyWjbg==":"porto-da-beira-mozambique.jpg","3kiZJe/0PH04RcuLw+yKaw==":"adobestock-271683243.png","vvsGsUX63GM/PxH7MD5EEw==":"mbr.jpg","J9Uye7P9bFfZG/N9v3Dlhw==":"images-4.jpg","q0Wkn8S4E9/aiPrFwbe5+Q==":"images-4.jpeg","HvwBh6SJvD4Mh66XUh7bOA==":"consultoria-em-recursos-humano-20221206164408.png","xpm59cr2TzbwcKTtYzURtw==":"images-5.jpeg","K7qMWm6SW7QYzOcqFCScBw==":"mbr-1.jpg","AMBAPmXM3NjOyU7x1Yvvcg==":"mbr-2.jpg","9dYSw4gXW6aMgYxIsSq0/w==":"mbr-3.jpg","3TGn7fFQJiHhuekypVs5rA==":"mbr-4.jpg","ew/jUVorzhC+uC+SxOaggw==":"mbr-4.jpeg","z6F22kUwir4fZ3qRDiRzbA==":"teste-1-page-1.jpg","q0VDGHHjGnfwk03imurXgw==":"teste-1-page-1.jpeg","JkMShRHtintpKWf4A+/O9A==":"teste-2-page-1.jpeg","xB/xtg+4OgxP9CzDbWUcbg==":"teste-3-page-1.jpeg","UXCxHIcHyCXn9KKZfIjX8g==":"teste-2-page-2.jpeg","mHgznhhY5nIrRam/G0PJiQ==":"teste-3-page-2.jpeg","pcQDSXlyiR4bNcMLP9ui+g==":"teste-3-page-3.jpeg","B+/1ZOgrOcF+hxr7aTslZw==":"teste-3-page-4.jpeg","WNmzejSc+ppgT3E6p7h06g==":"teste-4-page-1.jpeg","ts1LfxLHcBqQEDTjDSdR9A==":"teste-4-page-2.jpeg","JDth1jC8gDGgPCohNGhZ7g==":"teste-4-page-3.jpeg","mRyAJYZ+A3gOeE55E989Lg==":"blog-conheca-4-tipos-de-consultoria-para-empresas.jpg","tkfA0fWaPiR+qfFumHE4AQ==":"kalgoorlie-open-cast-mine.jpg","jrLcivmmx9P7Yptj/pIluA==":"estudo-rochas-geologo.webp","dWGJ4D0oKd6I8rjBTD5JqA==":"images-5.jpg","M4giH6nlkOGrjpmIN01Zrg==":"financeiro-e-contabil.jpg","hqvLkJwJUD0Vqg/tmxsUzQ==":"equipe-de-negocios-bem-sucedido-e-feliz-2-scaled.jpg","0Eyehx5DH5LZiUnd+/b6Gw==":"smiling-businessman-presenting-chart-scaled.jpg","DI8dEgkcGltJmtgUd2QzMg==":"smiling-businessman-presenting-chart-scaled.jpeg","cbVYq+077B0jKtHzFdvUtw==":"smiling-businessman-presenting-chart-scaled-1.jpeg","OA+ftQMye5wmyYh70x6DPw==":"smiling-businessman-presenting-chart-scaled-2.jpeg","vRzL1IlMHLdhQOwJvWKdKw==":"mbr-5.jpg","w7OGKOlGU7TL4rdxgFSVFQ==":"mbr-6.jpg","wmiHAZvFMZB6n/pvjMCrjQ==":"mbr-7.jpg","9EQ6lSnch1N6bvfVD2QcZQ==":"mbr-8.jpg","nCUIRSsbqIKzAkmZg7Cnuw==":"mbr-9.jpg","+4OcsKPfqMhCJ2o2rqXGMw==":"blog-conheca-4-tipos-de-consultoria-para-empresas-850x441.jpg","NFv3rhhVVF4ZGlPY5s6lXA==":"blog-conheca-4-tipos-de-consultoria-para-empresas-850x441.jpeg","XccRMxWD+rXd7DRizxvm6A==":"kalgoorlie_open_cast_mine-768x512.jpg","gfJgyizKj5tY2mMwmD7N6Q==":"equipe-de-negocios-bem-sucedido-e-feliz-2-scaled-2000x1337.jpg","V7u9xFVsMq0RjXAgiDZzbQ==":"smiling-businessman-presenting-chart-scaled-2000x1335.jpg"}